setup.py
envtransfer/__init__.py
envtransfer/core.py
envtransfer/exception.py
envtransfer/help.py
envtransfer/settings.py
envtransfer.egg-info/PKG-INFO
envtransfer.egg-info/SOURCES.txt
envtransfer.egg-info/dependency_links.txt
envtransfer.egg-info/entry_points.txt
envtransfer.egg-info/top_level.txt