Metadata-Version: 1.0
Name: envtransfer
Version: 0.12
Summary: Transfer your environment between computers using Yandex Disk.
Home-page: https://pypi.python.org/pypi/envtransfer/0.11
Author: Yuri Bukatkin
Author-email: iturs@yandex.ru
License: UNKNOWN
Platform: UNKNOWN
